steffs_pharmacy/_init_.py
steffs_pharmacy/billing.py
steffs_pharmacy/customerorder.py
steffs_pharmacy/displayinvoicereport.py
steffs_pharmacy/displaystockreport.py
steffs_pharmacy/inventoryupdate.py
steffs_pharmacy/invoiceupdate.py
steffs_pharmacy/main.py
steffs_pharmacy/placingcustomerorder.py
steffs_pharmacy/searchdrugs.py
steffs_pharmacy/output/main/_init_.py
steffs_pharmacy-0.0.1.dist-info/METADATA
steffs_pharmacy-0.0.1.dist-info/WHEEL
steffs_pharmacy-0.0.1.dist-info/top_level.txt
steffs_pharmacy-0.0.1.dist-info/RECORD
